{
  "documents": [
    {
      "file_name": "HR_Employee_Handbook.pdf",
      "file_path": "~/Projects/RAG-Capstone/Company-Data/HR_Employee_Handbook.pdf",
      "document_type": "HR Policy",
      "category": "Internal",
      "description": "Official policy document covering PTO, dress code, employee discounts, and disciplinary procedures for staff.",
      "sensitivity": "High"
    },
    {
      "file_name": "Customer_Return_Policy.pdf",
      "file_path": "~/Projects/RAG-Capstone/Company-Data/Customer_Return_Policy.pdf",
      "document_type": "Customer Policy",
      "category": "External",
      "description": "Guidelines for customer returns and exchanges, including time limits (30/45 days) and conditions for specific items like pottery and books.",
      "sensitivity": "Low"
    },
    {
      "file_name": "Q3_2024_Sales_Summary.pdf",
      "file_path": "~/Projects/RAG-Capstone/Company-Data/Q3_2024_Sales_Summary.pdf",
      "document_type": "Financial Data",
      "category": "Internal",
      "description": "Quarterly summary of store performance, including total revenue, best-selling categories, and staffing notes.",
      "sensitivity": "Medium"
    },
    {
      "file_name": "Store_Operations_Guide.pdf",
      "file_path": "~/Projects/RAG-Capstone/Company-Data/Store_Operations_Guide.pdf",
      "document_type": "Operations Manual",
      "category": "Internal",
      "description": "Details on key suppliers (Schwinn Bike Parts), equipment, store cleaning, and manager contact information.",
      "sensitivity": "Medium"
    },
    {
      "file_name": "Customer_FAQ.pdf",
      "file_path": "~/Projects/RAG-Capstone/Company-Data/Customer_FAQ.pdf",
      "document_type": "Customer Service",
      "category": "External",
      "description": "Answers to common customer questions about gift shipping, events, repairs, and accepted payment methods.",
      "sensitivity": "Low"
    },
    {
      "file_name": "Winter_Warmer_Promotion.pdf",
      "file_path": "~/Projects/RAG-Capstone/Company-Data/Winter_Warmer_Promotion.pdf",
      "document_type": "Marketing",
      "category": "External",
      "description": "Announcement for the seasonal sales event, including 20% off items, the Spiced Maple Latte special, and the $75 purchase gift offer.",
      "sensitivity": "Low"
    }
  ]
}